oval_graph/__init__.py
oval_graph/_builder_html_graph.py
oval_graph/_xml_parser_comments.py
oval_graph/_xml_parser_oval_scan_definitions.py
oval_graph/_xml_parser_test_info.py
oval_graph/command_line.py
oval_graph/exceptions.py
oval_graph/xml_parser.py
oval_graph/arf_xml_parser/__init__.py
oval_graph/arf_xml_parser/_comments.py
oval_graph/arf_xml_parser/_oval_scan_definitions.py
oval_graph/arf_xml_parser/_test_info.py
oval_graph/arf_xml_parser/arf_xml_parser.py
oval_graph/arf_xml_parser/global_namespaces.py
oval_graph/command_line_client/__init__.py
oval_graph/command_line_client/arf_to_html.py
oval_graph/command_line_client/arf_to_json.py
oval_graph/command_line_client/client.py
oval_graph/command_line_client/client_arf_input.py
oval_graph/command_line_client/client_html_output.py
oval_graph/command_line_client/client_json_input.py
oval_graph/command_line_client/json_to_html.py
oval_graph/html_builder/__init__.py
oval_graph/html_builder/graph.py
oval_graph/oval_tree/__init__.py
oval_graph/oval_tree/builder.py
oval_graph/oval_tree/converter.py
oval_graph/oval_tree/evaluate.py
oval_graph/oval_tree/oval_node.py
oval_graph/oval_tree/oval_result.py
oval_graph/parts/bootstrapScript.txt
oval_graph/parts/bootstrapStyle.txt
oval_graph/parts/css.txt
oval_graph/parts/jQueryScript.txt
oval_graph/parts/jsTreeScript.txt
oval_graph/parts/jsTreeStyle.txt
oval_graph/parts/script.js
oval_graph/schemas/arf/1.1/asset-identification_1.1.0.xsd
oval_graph/schemas/arf/1.1/asset-reporting-format_1.1.0.xsd
oval_graph/schemas/arf/1.1/reporting-core_1.1.0.xsd
oval_graph/schemas/arf/1.1/xAL.xsd
oval_graph/schemas/arf/1.1/xNL.xsd
oval_graph/schemas/common/catalog.xsd
oval_graph/schemas/common/xlink.xsd
oval_graph/schemas/common/xml.xsd
oval_graph/schemas/common/xmldsig-core-schema.xsd
oval_graph/schemas/cpe/2.0/cpe-dictionary_2.0.xsd
oval_graph/schemas/cpe/2.1/cpe-dictionary_2.1.xsd
oval_graph/schemas/cpe/2.2/cpe-dictionary_2.2.xsd
oval_graph/schemas/cpe/2.3/cpe-dictionary_2.3.xsd
oval_graph-1.3.3.dist-info/LICENSE
oval_graph-1.3.3.dist-info/METADATA
oval_graph-1.3.3.dist-info/WHEEL
oval_graph-1.3.3.dist-info/entry_points.txt
oval_graph-1.3.3.dist-info/top_level.txt
oval_graph-1.3.3.dist-info/RECORD
