Metadata-Version: 2.1
Name: oval-graph
Version: 1.3.3
Summary: Tool for visualization of SCAP rule evaluation results
Home-page: https://github.com/OpenSCAP/OVAL-visualization-as-graph
Author: Jan Rodak
Author-email: jrodak@redhat.com
License: Apache-2.0
Platform: UNKNOWN
Requires-Python: >=3.6
License-File: LICENSE
Requires-Dist: lxml
